yatp/__init__.py
yatp/yatp.py
yatp-0.1.0.dist-info/METADATA
yatp-0.1.0.dist-info/WHEEL
yatp-0.1.0.dist-info/RECORD
